openmetrics_liveness_probe/__init__.py
openmetrics_liveness_probe/conf.py
openmetrics_liveness_probe/openmetrics_liveness_probe.py
openmetrics_liveness_probe-0.2.0.dist-info/LICENSE
openmetrics_liveness_probe-0.2.0.dist-info/WHEEL
openmetrics_liveness_probe-0.2.0.dist-info/METADATA
openmetrics_liveness_probe-0.2.0.dist-info/RECORD
