Metadata-Version: 2.1
Name: openmetrics-liveness-probe
Version: 0.2.0
Summary: Library for getting the time when the service was last considered alive.
Home-page: https://github.com/Usetech/openmetrics-liveness-probe
License: MIT
Keywords: openmetrics,liveness_probe
Author: Daniil Nikitin
Author-email: dnikitin@usetech.ru
Requires-Python: >=3.8,<4
Classifier: License :: OSI Approved :: MIT License
Classifier: Programming Language :: Python :: 3
Classifier: Programming Language :: Python :: 3.8
Classifier: Programming Language :: Python :: 3.9
Classifier: Programming Language :: Python :: 3.10
Classifier: Programming Language :: Python :: 3.11
Requires-Dist: prometheus-client (>=0.9)
Requires-Dist: pydantic (>=1.8,<3.0)
Project-URL: Repository, https://github.com/Usetech/openmetrics-liveness-probe
